CITATION.cff
LICENSE
README.md
pyproject.toml
setup.py
flig/__init__.py
flig/flig.py
flig.egg-info/PKG-INFO
flig.egg-info/SOURCES.txt
flig.egg-info/dependency_links.txt
flig.egg-info/requires.txt
flig.egg-info/top_level.txt
tests/test_attribute.py