Metadata-Version: 2.4
Name: flig
Version: 0.1.0
Summary: Frequency-domain model analysis package
Home-page: https://gitlab.com/paulabraham.graeve/flex
Author: Paul Gräve
License: MIT
Classifier: Programming Language :: Python :: 3
Classifier: License :: OSI Approved :: MIT License
License-File: LICENSE
License-File: CITATION.cff
Requires-Dist: torch>=2.0.0
Requires-Dist: numpy>=1.21.0
Requires-Dist: captum>=0.6.0
Provides-Extra: academic
Requires-Dist: howfairis>=0.20.0; extra == "academic"
Dynamic: author
Dynamic: classifier
Dynamic: description
Dynamic: description-content-type
Dynamic: home-page
Dynamic: license
Dynamic: license-file
Dynamic: provides-extra
Dynamic: requires-dist
Dynamic: summary
